{
  "$schema": "https://developer.microsoft.com/json-schemas/fabric/item/report/definition/visualContainer/2.7.0/schema.json",
  "name": "btn-dept-breakdown",
  "position": {
    "x": 880,
    "y": 470,
    "width": 180,
    "height": 40,
    "z": 19002,
    "tabOrder": 17
  },
  "visual": {
    "visualContainerObjects": {
      "visualLink": [
        {
          "properties": {
            "show": {
              "expr": {
                "Literal": {
                  "Value": "true"
                }
              }
            },
            "type": {
              "expr": {
                "Literal": {
                  "Value": "'PageNavigation'"
                }
              }
            },
            "navigationSection": {
              "expr": {
                "Literal": {
                  "Value": "'9cbe4eb03f6190f61d23'"
                }
              }
            },
            "tooltip": {
              "expr": {
                "Literal": {
                  "Value": "'Go to Department Breakdown'"
                }
              }
            }
          }
        }
      ],
      "title": [
        {
          "properties": {
            "show": {
              "expr": {
                "Literal": {
                  "Value": "true"
                }
              }
            },
            "text": {
              "expr": {
                "Literal": {
                  "Value": "'Department Breakdown'"
                }
              }
            }
          }
        }
      ]
    },
    "visualType": "actionButton"
  }
}